README.rst
setup.py
SyncHg.egg-info/PKG-INFO
SyncHg.egg-info/SOURCES.txt
SyncHg.egg-info/dependency_links.txt
SyncHg.egg-info/entry_points.txt
SyncHg.egg-info/not-zip-safe
SyncHg.egg-info/requires.txt
SyncHg.egg-info/top_level.txt
synchg/__init__.py
synchg/remote.py
synchg/repo.py
synchg/script.py
synchg/sync.py
synchg/utils.py