Metadata-Version: 1.0
Name: SyncHg
Version: 1.0.0
Summary: A simple script & library to handle syncing remote mercuial repositories
Home-page: http://synchg.readthedocs.org/
Author: Graeme Coupar
Author-email: grambo@grambo.me.uk
License: BSD
Platform: any
Classifier: Development Status :: 4 - Beta
Classifier: Environment :: Console
Classifier: Intended Audience :: Developers
Classifier: License :: OSI Approved :: BSD License
Classifier: Operating System :: OS Independent
Classifier: Programming Language :: Python
Classifier: Topic :: Utilities
Classifier: Topic :: Software Development :: Version Control
Classifier: Topic :: Software Development :: Libraries :: Python Modules
